[
  {
    "propertyImg": "https://i.ibb.co/dkVGSrH/home1.jpg",
    "propertyTitle": "Modern City Apartment",
    "propertyLocation": "Downtown, Metropolis",
    "propertyPriceRange": [3000, 4800],
    "propertyVerificationStatus": "verified",
    "propertyFeatures": ["Balcony", "Smart Home System", "Fitness Center"],
    "propertyBeauty": "Stunning city skyline views",
    "agentImg": "https://i.ibb.co/Yb95dr4/1.png",
    "agentName": "John Smith",
    "agentEmail": "john.smith@example.com"
  },
  {
    "propertyImg": "https://i.ibb.co/CsBZXdr/home2.jpg",
    "propertyTitle": "Cozy Suburban Cottage",
    "propertyLocation": "Tranquil Suburbia",
    "propertyPriceRange": [2500, 4000],
    "propertyVerificationStatus": "verified",
    "propertyFeatures": ["Spacious Garden", "Fireplace", "High Ceilings"],
    "propertyBeauty": "Charming garden and peaceful surroundings",
    "agentImg": "https://i.ibb.co/rcvg6px/2.png",
    "agentName": "Emily Johnson",
    "agentEmail": "emily.johnson@example.com"
  },
  {
    "propertyImg": "https://i.ibb.co/X8YbmGR/home3.jpg",
    "propertyTitle": "Luxury Beachfront Villa",
    "propertyLocation": "Sunset Bay",
    "propertyPriceRange": [8000, 12000],
    "propertyVerificationStatus": "verified",
    "propertyFeatures": [
      "Private Beach Access",
      "Infinity Pool",
      "Outdoor Kitchen"
    ],
    "propertyBeauty": "Breathtaking ocean views and private beachfront",
    "agentImg": "https://i.ibb.co/MPF9N0G/15.png",
    "agentName": "Michael Rodriguez",
    "agentEmail": "michael.rodriguez@example.com"
  },
  {
    "propertyImg": "https://i.ibb.co/KDJTnCJ/home4.jpg",
    "propertyTitle": "Rustic Mountain Retreat",
    "propertyLocation": "Serene Mountainside",
    "propertyPriceRange": [3500, 5500],
    "propertyVerificationStatus": "verified",
    "propertyFeatures": [
      "Wood Burning Stove",
      "Hiking Trails Access",
      "Panoramic Views"
    ],
    "propertyBeauty": "Idyllic mountain scenery and tranquility",
    "agentImg": "https://i.ibb.co/BLyHCDY/4.png",
    "agentName": "Jessica Carter",
    "agentEmail": "jessica.carter@example.com"
  },
  {
    "propertyImg": "https://i.ibb.co/tzbPD5N/home5.jpg",
    "propertyTitle": "Urban Loft with a View",
    "propertyLocation": "Artsy District",
    "propertyPriceRange": [4000, 6000],
    "propertyVerificationStatus": "verified",
    "propertyFeatures": ["Exposed Brick Walls", "Large Windows", "Roof Deck"],
    "propertyBeauty": "Artistic vibes and panoramic cityscapes",
    "agentImg": "https://i.ibb.co/QfxN5Kz/5.png",
    "agentName": "Daniel Lee",
    "agentEmail": "daniel.lee@example.com"
  },
  {
    "propertyImg": "https://i.ibb.co/bFS9bP0/home6.jpg",
    "propertyTitle": "Mansion in the Woods",
    "propertyLocation": "Secluded Forest",
    "propertyPriceRange": [10000, 15000],
    "propertyVerificationStatus": "verified",
    "propertyFeatures": ["Private Forest Trail", "Indoor Pool", "Home Theater"],
    "propertyBeauty": "Enchanting forest surroundings and luxurious amenities",
    "agentImg": "https://i.ibb.co/jhnkRH0/6.png",
    "agentName": "Sophia Brown",
    "agentEmail": "sophia.brown@example.com"
  },
  {
    "propertyImg": "https://i.ibb.co/L1g875c/home7.jpg",
    "propertyTitle": "Historic Townhouse",
    "propertyLocation": "Old Town Charm",
    "propertyPriceRange": [6000, 9000],
    "propertyVerificationStatus": "verified",
    "propertyFeatures": [
      "Original Architecture",
      "Courtyard Garden",
      "Antique Details"
    ],
    "propertyBeauty": "Preserved historical charm and elegant design",
    "agentImg": "https://i.ibb.co/XWMFnfH/7.png",
    "agentName": "Ryan Miller",
    "agentEmail": "ryan.miller@example.com"
  },
  {
    "propertyImg": "https://i.ibb.co/1swQtcv/home8.jpg",
    "propertyTitle": "Penthouse Paradise",
    "propertyLocation": "Skyline Heights",
    "propertyPriceRange": [12000, 18000],
    "propertyVerificationStatus": "verified",
    "propertyFeatures": [
      "Private Terrace",
      "Skyline Views",
      "High-end Finishes"
    ],
    "propertyBeauty": "Exclusive penthouse living with unparalleled city views",
    "agentImg": "https://i.ibb.co/Xb1cHtn/8.png",
    "agentName": "Olivia White",
    "agentEmail": "olivia.white@example.com"
  },
  {
    "propertyImg": "https://i.ibb.co/cc0ybL4/home9.jpg",
    "propertyTitle": "Contemporary Lake House",
    "propertyLocation": "Tranquil Lakeside",
    "propertyPriceRange": [7000, 10000],
    "propertyVerificationStatus": "verified",
    "propertyFeatures": [
      "Dock Access",
      "Open Concept Design",
      "Scenic Windows"
    ],
    "propertyBeauty": "Panoramic lake views and modern design",
    "agentImg": "https://i.ibb.co/QfXGxQG/9.png",
    "agentName": "David Anderson",
    "agentEmail": "david.anderson@example.com"
  },
  {
    "propertyImg": "https://i.ibb.co/sVnSwzR/home10.jpg",
    "propertyTitle": "Sleek Urban Studio",
    "propertyLocation": "City Center",
    "propertyPriceRange": [2000, 3500],
    "propertyVerificationStatus": "verified",
    "propertyFeatures": ["Efficient Layout", "Modern Appliances", "City Views"],
    "propertyBeauty": "Smart and stylish city living",
    "agentImg": "https://i.ibb.co/VWwv8jh/10.png",
    "agentName": "Emma Wilson",
    "agentEmail": "emma.wilson@example.com"
  },
  {
    "propertyImg": "https://i.ibb.co/nn1br5k/home11.jpg",
    "propertyTitle": "Country Farmhouse",
    "propertyLocation": "Rural Retreat",
    "propertyPriceRange": [4500, 7000],
    "propertyVerificationStatus": "verified",
    "propertyFeatures": ["Wrap-around Porch", "Barn", "Expansive Fields"],
    "propertyBeauty": "Quaint farmhouse charm and vast open spaces",
    "agentImg": "https://i.ibb.co/JtZ2jXH/11.png",
    "agentName": "Christopher Davis",
    "agentEmail": "christopher.davis@example.com"
  },
  {
    "propertyImg": "https://i.ibb.co/TYT1m3d/home12.jpg",
    "propertyTitle": "Elegant Townhome",
    "propertyLocation": "Sophisticated Suburb",
    "propertyPriceRange": [5000, 8000],
    "propertyVerificationStatus": "verified",
    "propertyFeatures": [
      "Gourmet Kitchen",
      "Private Patio",
      "Luxurious Finishes"
    ],
    "propertyBeauty": "Classic elegance and modern amenities",
    "agentImg": "https://i.ibb.co/sRZchZr/12.png",
    "agentName": "Ava Robinson",
    "agentEmail": "ava.robinson@example.com"
  }
]
